archivus/__init__.py
archivus-0.1.1.dist-info/WHEEL
archivus-0.1.1.dist-info/entry_points.txt
archivus-0.1.1.dist-info/METADATA
archivus-0.1.1.dist-info/RECORD
