Metadata-Version: 2.3
Name: archivus
Version: 0.1.1
Summary: Add your description here
Author: Eivind Teig
Author-email: Eivind Teig <eivind.teig@gmail.com>
Requires-Python: >=3.14
